obfus/__init__.py
obfus/engine.py
obfus/py.typed
obfus-3.7.2.dist-info/licenses/LICENSE
obfus-3.7.2.dist-info/METADATA
obfus-3.7.2.dist-info/WHEEL
obfus-3.7.2.dist-info/entry_points.txt
obfus-3.7.2.dist-info/top_level.txt
obfus-3.7.2.dist-info/RECORD
