Metadata-Version: 2.4
Name: obfus
Version: 3.7.2
Summary: A comprehensive Python code obfuscation engine
Author-email: Farshid Ashouri <farsheed.ashouri@gmail.com>
License-Expression: MIT
Project-URL: Homepage, https://github.com/rodmena-limited/obfus
Project-URL: Documentation, https://github.com/rodmena-limited/obfus#readme
Project-URL: Repository, https://github.com/rodmena-limited/obfus.git
Project-URL: Issues, https://github.com/rodmena-limited/obfus/issues
Project-URL: Changelog, https://github.com/rodmena-limited/obfus/blob/main/CHANGELOG.md
Keywords: obfuscation,obfuscator,python,protect,encrypt,security,code-protection,ast,minify
Classifier: Development Status :: 5 - Production/Stable
Classifier: Environment :: Console
Classifier: Intended Audience :: Developers
Classifier: Operating System :: OS Independent
Classifier: Programming Language :: Python
Classifier: Programming Language :: Python :: 3
Classifier: Programming Language :: Python :: 3.9
Classifier: Programming Language :: Python :: 3.10
Classifier: Programming Language :: Python :: 3.11
Classifier: Programming Language :: Python :: 3.12
Classifier: Programming Language :: Python :: 3.13
Classifier: Topic :: Security
Classifier: Topic :: Software Development :: Build Tools
Classifier: Topic :: Software Development :: Code Generators
Classifier: Topic :: Software Development :: Pre-processors
Classifier: Topic :: Utilities
Classifier: Typing :: Typed
Requires-Python: >=3.9
License-File: LICENSE
Provides-Extra: dev
Requires-Dist: pytest>=7.0; extra == "dev"
Requires-Dist: pytest-cov>=4.0; extra == "dev"
Requires-Dist: ruff>=0.1.0; extra == "dev"
Requires-Dist: mypy>=1.0; extra == "dev"
Requires-Dist: black>=23.0; extra == "dev"
Dynamic: license-file
